hafoo_trade_sdk_test/__init__.py
hafoo_trade_sdk_test/acc_trade_info.py
hafoo_trade_sdk_test/constant.py
hafoo_trade_sdk_test/device_info_qry.py
hafoo_trade_sdk_test/encryption.py
hafoo_trade_sdk_test/example.py
hafoo_trade_sdk_test/fund_qry.py
hafoo_trade_sdk_test/get_ip.py
hafoo_trade_sdk_test/model.py
hafoo_trade_sdk_test/order_client.py
hafoo_trade_sdk_test/order_deal_qry.py
hafoo_trade_sdk_test/order_fare_qry.py
hafoo_trade_sdk_test/order_modify.py
hafoo_trade_sdk_test/order_place.py
hafoo_trade_sdk_test/order_qry.py
hafoo_trade_sdk_test/pos_qry.py
hafoo_trade_sdk_test/test.py
hafoo_trade_sdk_test-1.0.12.dist-info/licenses/LICENSE
hafoo_trade_sdk_test-1.0.12.dist-info/METADATA
hafoo_trade_sdk_test-1.0.12.dist-info/WHEEL
hafoo_trade_sdk_test-1.0.12.dist-info/top_level.txt
hafoo_trade_sdk_test-1.0.12.dist-info/RECORD
