Metadata-Version: 2.4
Name: hafoo_trade_sdk_test
Version: 1.0.12
Summary: Order Service SDK for Python
Home-page: https://github.com/KuBoy/hafoo_trade_sdk_test
Author: KuBoy
Author-email: 1757378111@qq.com
Classifier: Programming Language :: Python :: 3
Classifier: License :: OSI Approved :: MIT License
Classifier: Operating System :: OS Independent
Requires-Python: >=3.6
License-File: LICENSE
Requires-Dist: requests>=2.25.1
Requires-Dist: cryptography>=46.0.1
Dynamic: author
Dynamic: author-email
Dynamic: classifier
Dynamic: description
Dynamic: description-content-type
Dynamic: home-page
Dynamic: license-file
Dynamic: requires-dist
Dynamic: requires-python
Dynamic: summary
